ArcheanBlueprints/Block.py
ArcheanBlueprints/Blueprint.py
ArcheanBlueprints/Component.py
ArcheanBlueprints/Enums.py
ArcheanBlueprints/Frame.py
ArcheanBlueprints/Pipes.py
ArcheanBlueprints/__init__.py
archeanblueprints-0.0.2.dist-info/licenses/LICENSE
archeanblueprints-0.0.2.dist-info/METADATA
archeanblueprints-0.0.2.dist-info/WHEEL
archeanblueprints-0.0.2.dist-info/top_level.txt
archeanblueprints-0.0.2.dist-info/RECORD
