Metadata-Version: 2.4
Name: ArcheanBlueprints
Version: 0.0.2
Summary: A library for extracting and optimizing Archean blueprints.
Home-page: https://github.com/Marlo3110/ArcheanBlueprints
License-File: LICENSE
Provides-Extra: dev
Requires-Dist: twine>=4.0.2; extra == "dev"
Dynamic: description
Dynamic: description-content-type
Dynamic: home-page
Dynamic: license-file
Dynamic: provides-extra
Dynamic: summary
